{
	"data":{"pop":[
	{"img":"http://localhost/22/imgs/9.jpg","name":"流行1","price":"111","id":1},
	{"img":"http://localhost/22/imgs/9.jpg","name":"流行2","price":"111","id":1},
	{"img":"http://localhost/22/imgs/9.jpg","name":"流行3","price":"111","id":1},
	{"img":"http://localhost/22/imgs/9.jpg","name":"流行4","price":"111","id":1},
	{"img":"http://localhost/22/imgs/9.jpg","name":"流行5","price":"111","id":1},
	{"img":"http://localhost/22/imgs/9.jpg","name":"流行6","price":"111","id":1},
	{"img":"http://localhost/22/imgs/9.jpg","name":"流行7","price":"111","id":1},
	{"img":"http://localhost/22/imgs/9.jpg","name":"流行1","price":"111","id":1},
	{"img":"http://localhost/22/imgs/9.jpg","name":"流行2","price":"111","id":1},
	{"img":"http://localhost/22/imgs/9.jpg","name":"流行3","price":"111","id":1},
	{"img":"http://localhost/22/imgs/9.jpg","name":"流行4","price":"111","id":1},
	{"img":"http://localhost/22/imgs/9.jpg","name":"流行5","price":"111","id":1},
	{"img":"http://localhost/22/imgs/9.jpg","name":"流行6","price":"111","id":1},
	{"img":"http://localhost/22/imgs/9.jpg","name":"流行1","price":"111","id":1},
	{"img":"http://localhost/22/imgs/9.jpg","name":"流行2","price":"111","id":1},
	{"img":"http://localhost/22/imgs/9.jpg","name":"流行3","price":"111","id":1},
	{"img":"http://localhost/22/imgs/9.jpg","name":"流行4","price":"111","id":1},
	{"img":"http://localhost/22/imgs/9.jpg","name":"流行5","price":"111","id":1},
	{"img":"http://localhost/22/imgs/9.jpg","name":"流行6","price":"111","id":1},
	{"img":"http://localhost/22/imgs/9.jpg","name":"流行1","price":"111","id":1},
	{"img":"http://localhost/22/imgs/9.jpg","name":"流行2","price":"111","id":1},
	{"img":"http://localhost/22/imgs/9.jpg","name":"流行3","price":"111","id":1},
	{"img":"http://localhost/22/imgs/9.jpg","name":"流行4","price":"111","id":1},
	{"img":"http://localhost/22/imgs/9.jpg","name":"流行5","price":"111","id":1},
	{"img":"http://localhost/22/imgs/9.jpg","name":"流行6","price":"111","id":1},
	{"img":"http://localhost/22/imgs/9.jpg","name":"流行1","price":"111","id":1},
	{"img":"http://localhost/22/imgs/9.jpg","name":"流行2","price":"111","id":1},
	{"img":"http://localhost/22/imgs/9.jpg","name":"流行3","price":"111","id":1},
	{"img":"http://localhost/22/imgs/9.jpg","name":"流行4","price":"111","id":1},
	{"img":"http://localhost/22/imgs/9.jpg","name":"流行5","price":"111","id":1},
	{"img":"http://localhost/22/imgs/9.jpg","name":"流行6","price":"111","id":1},
	{"img":"http://localhost/22/imgs/9.jpg","name":"流行1","price":"111","id":1},
	{"img":"http://localhost/22/imgs/9.jpg","name":"流行2","price":"111","id":1},
	{"img":"http://localhost/22/imgs/9.jpg","name":"流行3","price":"111","id":1},
	{"img":"http://localhost/22/imgs/9.jpg","name":"流行4","price":"111","id":1},
	{"img":"http://localhost/22/imgs/9.jpg","name":"流行5","price":"111","id":1},
	{"img":"http://localhost/22/imgs/9.jpg","name":"流行6","price":"111","id":1}
],"news":[
	{"img":"http://localhost/22/imgs/10.jpg","name":"古典1","price":"222","id":2},
	{"img":"http://localhost/22/imgs/10.jpg","name":"古典2","price":"222","id":2},
	{"img":"http://localhost/22/imgs/10.jpg","name":"古典3","price":"222","id":2},
	{"img":"http://localhost/22/imgs/10.jpg","name":"古典4","price":"222","id":2},
	{"img":"http://localhost/22/imgs/10.jpg","name":"古典5","price":"222","id":2},
	{"img":"http://localhost/22/imgs/10.jpg","name":"古典6","price":"222","id":2},
	{"img":"http://localhost/22/imgs/10.jpg","name":"古典7","price":"222","id":2},
	{"img":"http://localhost/22/imgs/10.jpg","name":"古典8","price":"222","id":2}
],"sell":[
	{"img":"http://localhost/22/imgs/11.jpg","name":"款式1","price":"333","id":3},
	{"img":"http://localhost/22/imgs/11.jpg","name":"款式2","price":"333","id":3},
	{"img":"http://localhost/22/imgs/11.jpg","name":"款式3","price":"333","id":3},
	{"img":"http://localhost/22/imgs/11.jpg","name":"款式4","price":"333","id":3},
	{"img":"http://localhost/22/imgs/11.jpg","name":"款式5","price":"333","id":3},
	{"img":"http://localhost/22/imgs/11.jpg","name":"款式6","price":"333","id":3},
	{"img":"http://localhost/22/imgs/11.jpg","name":"款式7","price":"333","id":3},
	{"img":"http://localhost/22/imgs/11.jpg","name":"款式8","price":"333","id":3},
	{"img":"http://localhost/22/imgs/11.jpg","name":"款式9","price":"333","id":3}
]}
}